zkRg1/__init__.py
zkRg1/zkRg1.py
zkRg-0.0.2.dist-info/LICENCE.txt
zkRg-0.0.2.dist-info/METADATA
zkRg-0.0.2.dist-info/WHEEL
zkRg-0.0.2.dist-info/top_level.txt
zkRg-0.0.2.dist-info/RECORD
