Metadata-Version: 2.1
Name: zkRg
Version: 0.0.2
Summary: Trial
Home-page: UNKNOWN
Author: Zafer Kosar
Author-email: zafer.kosar.physics@gmail.com
License: MIT
Keywords: trial
Platform: UNKNOWN
Classifier: Development Status :: 4 - Beta
Classifier: Intended Audience :: Education
Classifier: License :: OSI Approved :: MIT License
Classifier: Programming Language :: Python :: 3
